pymupdf4llm/__init__.py
pymupdf4llm/versions_file.py
pymupdf4llm/helpers/get_text_lines.py
pymupdf4llm/helpers/multi_column.py
pymupdf4llm/helpers/progress.py
pymupdf4llm/helpers/pymupdf_rag.py
pymupdf4llm/llama/pdf_markdown_reader.py
pymupdf4llm_kuberlab-0.0.28.dist-info/LICENSE
pymupdf4llm_kuberlab-0.0.28.dist-info/METADATA
pymupdf4llm_kuberlab-0.0.28.dist-info/WHEEL
pymupdf4llm_kuberlab-0.0.28.dist-info/top_level.txt
pymupdf4llm_kuberlab-0.0.28.dist-info/RECORD
